{
  "id": "java-graph-representation",
  "moduleId": "graphs",
  "title": "Graph Representation: Adjacency List and Matrix",
  "description": "Beyond trees -- nodes that can connect to ANY other node, not just two children, represented two different ways in code.",
  "objectives": [
    "Understand a graph as nodes (vertices) and connections (edges), more general than a tree",
    "Represent a graph with an adjacency list (List of Lists / Map of Lists)",
    "Represent the same graph with an adjacency matrix, and compare trade-offs"
  ],
  "sections": [
    {
      "type": "heading",
      "text": "1. Beyond Trees: Arbitrary Connections"
    },
    {
      "type": "paragraph",
      "text": "Every tree in the Trees module had a strict rule: each node has AT MOST two children (or, for a Trie, one parent), and there's exactly one path from the root to any node. A graph drops these restrictions entirely -- any node can connect to any number of other nodes, in any pattern, including cycles."
    },
    {
      "type": "definition",
      "term": "Graph",
      "text": "A collection of vertices (nodes) connected by edges, with no restriction on how many connections a vertex can have or what shape those connections form."
    },
    {
      "type": "realLifeExample",
      "title": "Social network analogy",
      "text": "A tree is like a strict company org chart -- one boss per person. A graph is like a friendship network -- anyone can be friends with anyone, friendships can form loops (A-B-C-A), and there's no single 'root' friend everyone descends from."
    },
    {
      "type": "heading",
      "text": "2. Adjacency List: A List of Neighbors per Node"
    },
    {
      "type": "code",
      "lang": "java",
      "filename": "Main.java",
      "code": "import java.util.ArrayList;\nimport java.util.List;\n\npublic class Main {\n    public static void main(String[] args) {\n        int n = 5; // nodes 0 through 4\n        List<List<Integer>> adjList = new ArrayList<>();\n        for (int i = 0; i < n; i++) {\n            adjList.add(new ArrayList<>());\n        }\n\n        // Undirected edges: 0-1, 0-2, 1-3, 2-4\n        addEdge(adjList, 0, 1);\n        addEdge(adjList, 0, 2);\n        addEdge(adjList, 1, 3);\n        addEdge(adjList, 2, 4);\n\n        System.out.println(adjList);\n    }\n\n    static void addEdge(List<List<Integer>> adjList, int u, int v) {\n        adjList.get(u).add(v);\n        adjList.get(v).add(u); // undirected -- both directions\n    }\n}",
      "output": "[[1, 2], [0, 3], [0, 4], [1], [2]]",
      "retypePractice": true,
      "retypeId": "java-graph-adj-list"
    },
    {
      "type": "definition",
      "term": "Adjacency list",
      "text": "A graph representation where each node stores a list of its directly connected neighbors -- commonly a List of Lists, or a Map<Node, List<Node>> for non-integer node identities."
    },
    {
      "type": "note",
      "text": "adjList.get(0) is [1, 2] -- node 0 connects directly to nodes 1 and 2. For an UNDIRECTED edge (a connection with no direction, like a two-way friendship), we add the connection in BOTH directions, as addEdge does here."
    },
    {
      "type": "heading",
      "text": "3. Adjacency Matrix: A Grid of Connections"
    },
    {
      "type": "code",
      "lang": "java",
      "filename": "Main.java",
      "code": "public class Main {\n    public static void main(String[] args) {\n        int n = 5;\n        int[][] adjMatrix = new int[n][n];\n\n        addEdge(adjMatrix, 0, 1);\n        addEdge(adjMatrix, 0, 2);\n        addEdge(adjMatrix, 1, 3);\n        addEdge(adjMatrix, 2, 4);\n\n        for (int[] row : adjMatrix) {\n            System.out.println(java.util.Arrays.toString(row));\n        }\n    }\n\n    static void addEdge(int[][] adjMatrix, int u, int v) {\n        adjMatrix[u][v] = 1;\n        adjMatrix[v][u] = 1;\n    }\n}",
      "output": "[0, 1, 1, 0, 0]\n[1, 0, 0, 1, 0]\n[1, 0, 0, 0, 1]\n[0, 1, 0, 0, 0]\n[0, 0, 1, 0, 0]",
      "retypePractice": true,
      "retypeId": "java-graph-adj-matrix"
    },
    {
      "type": "definition",
      "term": "Adjacency matrix",
      "text": "A graph representation using an n x n 2D array (recall 2D Arrays), where a 1 (or edge weight) at [i][j] means an edge exists between node i and node j, and 0 means no edge."
    },
    {
      "type": "note",
      "text": "adjMatrix[0][1] = 1 and adjMatrix[1][0] = 1 both being set represents the same undirected edge -- notice the matrix here is symmetric across its diagonal, which is always true for undirected graphs."
    },
    {
      "type": "heading",
      "text": "4. Comparing the Two Representations"
    },
    {
      "type": "table",
      "title": "Adjacency list vs adjacency matrix",
      "headers": ["", "Adjacency List", "Adjacency Matrix"],
      "rows": [
        ["Space used", "O(V + E) -- proportional to actual edges", "O(V^2) -- always, regardless of edge count"],
        ["Check if edge (u,v) exists", "O(degree of u) -- scan u's neighbor list", "O(1) -- direct lookup adjMatrix[u][v]"],
        ["List all of a node's neighbors", "O(degree of u) -- already a list", "O(V) -- must scan the entire row"],
        ["Best for", "SPARSE graphs (few edges relative to nodes)", "DENSE graphs, or when edge-existence checks are frequent"]
      ]
    },
    {
      "type": "warning",
      "text": "Most real-world graphs (social networks, road maps, dependency graphs) are SPARSE -- each node connects to relatively few others, not everyone. For these, adjacency list's O(V + E) space is far more efficient than a matrix's guaranteed O(V^2), which is why adjacency list is the more common default choice in practice, including for the BFS and DFS lessons coming up next."
    },
    {
      "type": "commonMistakes",
      "title": "Common Beginner Mistakes",
      "items": [
        "Forgetting to add the edge in BOTH directions for an undirected graph -- adjList.get(u).add(v) alone only represents a one-way (directed) connection.",
        "Using an adjacency matrix by default for large, sparse graphs, wasting O(V^2) space when most of the matrix would just be zeros.",
        "Confusing a graph's generality with a tree's restrictions -- a graph can have cycles and multiple paths between nodes; a tree cannot.",
        "Assuming adjacency list gives O(1) edge-existence checks like a matrix does -- checking if v is a neighbor of u requires scanning u's list, not a direct lookup."
      ]
    },
    {
      "type": "interviewQuestions",
      "title": "Interview Questions",
      "questions": [
        {
          "question": "What is the key structural difference between a graph and a tree?",
          "answer": "A tree restricts each node to at most a fixed number of children (e.g. 2 for binary trees) with exactly one path from the root to any node and no cycles. A graph has no such restriction -- any node can connect to any number of others, and cycles are allowed."
        },
        {
          "question": "What is the space complexity of an adjacency list vs an adjacency matrix?",
          "answer": "An adjacency list uses O(V + E) space, proportional to the actual number of vertices and edges. An adjacency matrix always uses O(V^2) space, regardless of how many edges actually exist."
        },
        {
          "question": "When would an adjacency matrix be preferred over an adjacency list?",
          "answer": "When the graph is dense (edges close to the maximum possible) or when frequent O(1) edge-existence checks (\"is there an edge between u and v?\") matter more than saving space -- for sparse graphs, an adjacency list is generally more efficient."
        }
      ],
      "thirtySecondAnswer": "A graph generalizes a tree by removing restrictions on how nodes connect -- any node can link to any number of others, cycles are allowed, and there's no single root. Adjacency list represents this as a list of neighbors per node, using O(V + E) space -- efficient for the sparse graphs common in practice. Adjacency matrix represents it as an n x n grid where a 1 at [i][j] marks an edge, using O(V^2) space always, but giving O(1) edge-existence checks. Adjacency list is the more common default, especially for sparse graphs, and is what the upcoming BFS and DFS lessons build on."
    },
    {
      "type": "memoryTrick",
      "title": "Trick to Remember",
      "text": "Adjacency list = each person's own contact list -- only stores who THEY actually know. Adjacency matrix = a full seating chart marking every possible pair -- checks are instant, but the chart's size never shrinks even if most seats are empty."
    },
    {
      "type": "quickCheck",
      "title": "Quick Understanding Check",
      "questions": [
        "How does a graph differ structurally from a tree?",
        "What is the space complexity of an adjacency list vs an adjacency matrix?",
        "Why do you need to add an edge in both directions for an undirected graph's adjacency list?",
        "When would you prefer an adjacency matrix over an adjacency list?"
      ]
    },
    {
      "type": "leetcode",
      "id": "lc-1971",
      "number": 1971,
      "title": "Find if Path Exists in Graph",
      "difficulty": "Easy",
      "link": "https://leetcode.com/problems/find-if-path-exists-in-graph/",
      "problemStatement": "Given an undirected graph as an edge list and a source and destination node, return whether a path exists between them.",
      "examples": [
        { "input": "n = 3, edges = [[0,1],[1,2],[2,0]], source = 0, destination = 2", "output": "true" }
      ],
      "constraints": ["1 <= n <= 2 * 10^5", "0 <= edges.length <= 2 * 10^5"],
      "hints": ["Build an adjacency list, then run BFS or DFS from source and check if destination is ever visited."],
      "approaches": [
        {
          "label": "Optimal",
          "explanation": "Build an adjacency list from the edge list, then BFS from source, marking visited nodes, and check whether destination gets visited.",
          "code": "class Solution {\n    public boolean validPath(int n, int[][] edges, int source, int destination) {\n        List<List<Integer>> adj = new ArrayList<>();\n        for (int i = 0; i < n; i++) adj.add(new ArrayList<>());\n        for (int[] edge : edges) {\n            adj.get(edge[0]).add(edge[1]);\n            adj.get(edge[1]).add(edge[0]);\n        }\n        boolean[] visited = new boolean[n];\n        Queue<Integer> queue = new LinkedList<>();\n        queue.offer(source);\n        visited[source] = true;\n        while (!queue.isEmpty()) {\n            int node = queue.poll();\n            if (node == destination) return true;\n            for (int neighbor : adj.get(node)) {\n                if (!visited[neighbor]) {\n                    visited[neighbor] = true;\n                    queue.offer(neighbor);\n                }\n            }\n        }\n        return false;\n    }\n}",
          "output": "true",
          "timeComplexity": "O(V + E)",
          "spaceComplexity": "O(V + E)"
        }
      ]
    },
    {
      "type": "leetcode",
      "id": "lc-1791",
      "number": 1791,
      "title": "Find Center of Star Graph",
      "difficulty": "Easy",
      "link": "https://leetcode.com/problems/find-center-of-star-graph/",
      "problemStatement": "A star graph has one center node connected to every other node. Given its edges, return the center node.",
      "examples": [
        { "input": "edges = [[1,2],[2,3],[4,2]]", "output": "2", "explanation": "Node 2 appears in all three edges." }
      ],
      "constraints": ["3 <= n <= 10^5"],
      "hints": ["The center node appears in EVERY edge -- so it must appear in both of the first two edges.", "Just check which node of edges[0] also appears in edges[1]."],
      "approaches": [
        {
          "label": "Optimal",
          "explanation": "The center is the node shared between the first two edges -- no need to scan the whole list. Check if edges[0][0] equals either endpoint of edges[1]; if so that's the center, otherwise edges[0][1] is.",
          "code": "class Solution {\n    public int findCenter(int[][] edges) {\n        int a = edges[0][0], b = edges[0][1];\n        int c = edges[1][0], d = edges[1][1];\n        return (a == c || a == d) ? a : b;\n    }\n}",
          "output": "2",
          "timeComplexity": "O(1)",
          "spaceComplexity": "O(1)"
        }
      ]
    },
    {
      "type": "leetcode",
      "id": "lc-997",
      "number": 997,
      "title": "Find the Town Judge",
      "difficulty": "Easy",
      "link": "https://leetcode.com/problems/find-the-town-judge/",
      "problemStatement": "In a town of n people, trust is a list of [a, b] meaning a trusts b. The judge trusts nobody but is trusted by everyone else. Return the judge, or -1 if none exists.",
      "examples": [
        { "input": "n = 3, trust = [[1,3],[2,3]]", "output": "3", "explanation": "3 is trusted by 1 and 2, and trusts nobody -- exactly n-1 = 2 people trust them." },
        { "input": "n = 3, trust = [[1,3],[2,3],[3,1]]", "output": "-1", "explanation": "3 trusts 1, so 3 can't be the judge (judge must trust nobody), and no one else qualifies either." }
      ],
      "constraints": ["1 <= n <= 1000", "0 <= trust.length <= 10^4"],
      "hints": ["Track a net score per person: -1 for each outgoing trust (they trust someone), +1 for each incoming trust (someone trusts them).", "The judge is the unique person with score exactly n-1."],
      "approaches": [
        {
          "label": "Optimal",
          "explanation": "For each [a, b] in trust: decrement a's score (a trusts someone, disqualifying a) and increment b's score (someone trusts b). The judge is whoever ends with score n-1 (trusted by everyone else, trusts no one).",
          "code": "class Solution {\n    public int findJudge(int n, int[][] trust) {\n        int[] score = new int[n + 1];\n        for (int[] t : trust) {\n            score[t[0]]--;\n            score[t[1]]++;\n        }\n        for (int person = 1; person <= n; person++) {\n            if (score[person] == n - 1) return person;\n        }\n        return -1;\n    }\n}",
          "output": "3",
          "timeComplexity": "O(n + trust.length)",
          "spaceComplexity": "O(n)"
        }
      ]
    },
    {
      "type": "leetcode",
      "id": "lc-802",
      "number": 802,
      "title": "Keys and Rooms",
      "difficulty": "Medium",
      "link": "https://leetcode.com/problems/keys-and-rooms/",
      "problemStatement": "There are n rooms labeled 0 to n-1. Room 0 is unlocked initially. rooms[i] is a list of keys found in room i, each key opens the room with that number. Return whether all rooms can be visited.",
      "examples": [
        { "input": "rooms = [[1],[2],[3],[]]", "output": "true", "explanation": "Start in room 0, get key 1, go to room 1, get key 2, go to room 2, get key 3, go to room 3." }
      ],
      "constraints": ["n == rooms.length", "1 <= n <= 1000"],
      "hints": ["This is graph reachability from node 0: a directed edge exists from room i to every key found in it.", "DFS or BFS from room 0, collecting visited rooms, then check if all n rooms were reached."],
      "approaches": [
        {
          "label": "Optimal",
          "explanation": "Treat each room as a graph node and each key as a directed edge to that room. DFS from room 0, marking visited rooms, then check the visited count equals n.",
          "code": "class Solution {\n    public boolean canVisitAllRooms(List<List<Integer>> rooms) {\n        boolean[] visited = new boolean[rooms.size()];\n        dfs(0, rooms, visited);\n        for (boolean v : visited) {\n            if (!v) return false;\n        }\n        return true;\n    }\n\n    private void dfs(int room, List<List<Integer>> rooms, boolean[] visited) {\n        if (visited[room]) return;\n        visited[room] = true;\n        for (int key : rooms.get(room)) {\n            dfs(key, rooms, visited);\n        }\n    }\n}",
          "output": "true",
          "timeComplexity": "O(V + E)",
          "spaceComplexity": "O(V)"
        }
      ]
    }
  ],
  "codeExamples": [
    { "id": "java-graph-adj-list", "lang": "java", "filename": "Main.java", "code": "import java.util.ArrayList;\nimport java.util.List;\n\npublic class Main {\n    public static void main(String[] args) {\n        int n = 5; // nodes 0 through 4\n        List<List<Integer>> adjList = new ArrayList<>();\n        for (int i = 0; i < n; i++) {\n            adjList.add(new ArrayList<>());\n        }\n\n        // Undirected edges: 0-1, 0-2, 1-3, 2-4\n        addEdge(adjList, 0, 1);\n        addEdge(adjList, 0, 2);\n        addEdge(adjList, 1, 3);\n        addEdge(adjList, 2, 4);\n\n        System.out.println(adjList);\n    }\n\n    static void addEdge(List<List<Integer>> adjList, int u, int v) {\n        adjList.get(u).add(v);\n        adjList.get(v).add(u); // undirected -- both directions\n    }\n}", "output": "[[1, 2], [0, 3], [0, 4], [1], [2]]" },
    { "id": "java-graph-adj-matrix", "lang": "java", "filename": "Main.java", "code": "public class Main {\n    public static void main(String[] args) {\n        int n = 5;\n        int[][] adjMatrix = new int[n][n];\n\n        addEdge(adjMatrix, 0, 1);\n        addEdge(adjMatrix, 0, 2);\n        addEdge(adjMatrix, 1, 3);\n        addEdge(adjMatrix, 2, 4);\n\n        for (int[] row : adjMatrix) {\n            System.out.println(java.util.Arrays.toString(row));\n        }\n    }\n\n    static void addEdge(int[][] adjMatrix, int u, int v) {\n        adjMatrix[u][v] = 1;\n        adjMatrix[v][u] = 1;\n    }\n}", "output": "[0, 1, 1, 0, 0]\n[1, 0, 0, 1, 0]\n[1, 0, 0, 0, 1]\n[0, 1, 0, 0, 0]\n[0, 0, 1, 0, 0]" }
  ],
  "retypePractice": [
    { "id": "java-graph-adj-list", "reference": "import java.util.ArrayList;\nimport java.util.List;\n\npublic class Main {\n    public static void main(String[] args) {\n        int n = 5; // nodes 0 through 4\n        List<List<Integer>> adjList = new ArrayList<>();\n        for (int i = 0; i < n; i++) {\n            adjList.add(new ArrayList<>());\n        }\n\n        // Undirected edges: 0-1, 0-2, 1-3, 2-4\n        addEdge(adjList, 0, 1);\n        addEdge(adjList, 0, 2);\n        addEdge(adjList, 1, 3);\n        addEdge(adjList, 2, 4);\n\n        System.out.println(adjList);\n    }\n\n    static void addEdge(List<List<Integer>> adjList, int u, int v) {\n        adjList.get(u).add(v);\n        adjList.get(v).add(u); // undirected -- both directions\n    }\n}" },
    { "id": "java-graph-adj-matrix", "reference": "public class Main {\n    public static void main(String[] args) {\n        int n = 5;\n        int[][] adjMatrix = new int[n][n];\n\n        addEdge(adjMatrix, 0, 1);\n        addEdge(adjMatrix, 0, 2);\n        addEdge(adjMatrix, 1, 3);\n        addEdge(adjMatrix, 2, 4);\n\n        for (int[] row : adjMatrix) {\n            System.out.println(java.util.Arrays.toString(row));\n        }\n    }\n\n    static void addEdge(int[][] adjMatrix, int u, int v) {\n        adjMatrix[u][v] = 1;\n        adjMatrix[v][u] = 1;\n    }\n}" }
  ],
  "practiceQuestions": [],
  "interviewQuestions": true,
  "leetcode": [],
  "completionRules": {
    "requireAllSectionsViewed": true,
    "requireRetypeIds": ["java-graph-adj-list", "java-graph-adj-matrix"]
  }
}
